derange/__init__.py
derange/py.typed
derange-0.2.2.dist-info/METADATA
derange-0.2.2.dist-info/WHEEL
derange-0.2.2.dist-info/licenses/LICENSE
derange-0.2.2.dist-info/RECORD
