Metadata-Version: 2.3
Name: derange
Version: 0.2.2
Summary: Compress lists of integers to range objects
Project-URL: Source Code, https://github.com/jwodder/derange
Project-URL: Bug Tracker, https://github.com/jwodder/derange/issues
Author-email: John Thorvald Wodder II <derange@varonathe.org>
License: MIT
Keywords: compression,connected component,consecutive,distribution sort,gaps and islands,interval,range,sequential,sorting,sparse array,streak
Classifier: License :: OSI Approved :: MIT License
Classifier: Programming Language :: Python :: 3
Classifier: Programming Language :: Python :: 3 :: Only
Classifier: Programming Language :: Python :: 3.8
Classifier: Programming Language :: Python :: 3.9
Classifier: Programming Language :: Python :: 3.10
Classifier: Programming Language :: Python :: 3.11
Classifier: Programming Language :: Python :: 3.12
Classifier: Programming Language :: Python :: 3.13
Classifier: Programming Language :: Python :: Implementation :: CPython
Classifier: Programming Language :: Python :: Implementation :: PyPy
Classifier: Topic :: Utilities
Classifier: Typing :: Typed
Requires-Python: >=3.8
